pystatsbomb/__init__.py
pystatsbomb/api.py
pystatsbomb/free.py
pystatsbomb/helpers.py
pystatsbomb-0.1.0.dist-info/AUTHORS.rst
pystatsbomb-0.1.0.dist-info/LICENSE
pystatsbomb-0.1.0.dist-info/METADATA
pystatsbomb-0.1.0.dist-info/WHEEL
pystatsbomb-0.1.0.dist-info/top_level.txt
pystatsbomb-0.1.0.dist-info/RECORD
