Metadata-Version: 2.1
Name: pystatsbomb
Version: 0.1.0
Summary: Python port of the StatsBombR library
Home-page: https://github.com/ElSaico/pystatsbomb
Author: Bruno Marques
Author-email: bruno@bmarques.net
License: Mozilla Public License 2.0 (MPL 2.0)
Keywords: pystatsbomb
Platform: UNKNOWN
Classifier: Development Status :: 2 - Pre-Alpha
Classifier: Intended Audience :: Developers
Classifier: License :: OSI Approved :: Mozilla Public License 2.0 (MPL 2.0)
Classifier: Natural Language :: English
Classifier: Programming Language :: Python :: 2
Classifier: Programming Language :: Python :: 2.7
Classifier: Programming Language :: Python :: 3
Classifier: Programming Language :: Python :: 3.4
Classifier: Programming Language :: Python :: 3.5
Classifier: Programming Language :: Python :: 3.6
Classifier: Programming Language :: Python :: 3.7
